Metadata-Version: 1.1
Name: watchhub
Version: 2020.12.1
Summary: Communicate with the watchub API to find streams from IMDB IDs.
Home-page: https://github.com/imduffy15/python-watchhub/
Author: Ian Duffy
Author-email: ian@ianduffy.ie
License: MIT
Keywords: watchhub
Platform: UNKNOWN
Classifier: License :: OSI Approved :: MIT License
Classifier: Operating System :: OS Independent
Classifier: Programming Language :: Python :: 3
